CHANGELOG.md
LICENSE
MANIFEST.in
README.md
README.rst
setup.py
daapserver/__init__.py
daapserver/bonjour.py
daapserver/collection.pxd
daapserver/collection.pyx
daapserver/daap.pxd
daapserver/daap.pyx
daapserver/daap_data.py
daapserver/models.pxd
daapserver/models.pyx
daapserver/provider.py
daapserver/responses.pxd
daapserver/responses.pyx
daapserver/revision.pxd
daapserver/revision.pyx
daapserver/server.py
daapserver/utils.py
examples/ExampleServer.py
examples/RevisionServer.py
examples/SoundcloudServer.py
flask_daapserver.egg-info/PKG-INFO
flask_daapserver.egg-info/SOURCES.txt
flask_daapserver.egg-info/dependency_links.txt
flask_daapserver.egg-info/not-zip-safe
flask_daapserver.egg-info/requires.txt
flask_daapserver.egg-info/top_level.txt
tests/__init__.py
tests/test_collection.py
tests/test_daap.py
tests/test_models.py
tests/test_provider.py
tests/test_revision.py
utils/benchmark.py
utils/benchmark_store.py
utils/transformer.py