Metadata-Version: 1.1
Name: flask-daapserver
Version: 3.0.2
Summary: DAAP server framework implemented with Flask
Home-page: https://github.com/basilfx/flask-daapserver
Author: Bas Stottelaar
Author-email: basstottelaar@gmail.com
License: MIT
Keywords: daap flask daapserver itunes home sharing streaming
Platform: any
Classifier: Development Status :: 5 - Production/Stable
Classifier: Intended Audience :: Developers
Classifier: License :: OSI Approved :: MIT License
Classifier: Topic :: System :: Networking
Classifier: Topic :: Multimedia :: Sound/Audio :: Players
Classifier: Programming Language :: Python :: 2
Classifier: Programming Language :: Python :: 2.7
Classifier: Programming Language :: Cython
